reverse_forward_proxy/__init__.py
reverse_forward_proxy/cli.py
reverse_forward_proxy/server.py
tests/__init__.py
tests/conftest.py
tests/test_assumptions.py
tests/test_proxy.py
tests/lib/__init__.py
tests/lib/tls.py
reverse_forward_proxy-0.1.0.dist-info/LICENSE
reverse_forward_proxy-0.1.0.dist-info/METADATA
reverse_forward_proxy-0.1.0.dist-info/WHEEL
reverse_forward_proxy-0.1.0.dist-info/entry_points.txt
reverse_forward_proxy-0.1.0.dist-info/top_level.txt
reverse_forward_proxy-0.1.0.dist-info/RECORD
