Metadata-Version: 2.1
Name: reverse-forward-proxy
Version: 0.1.0
Summary: Reverse proxy for forward proxy
Home-page: https://github.com/chrahunt/reverse-forward-proxy
Author: Chris Hunt
Author-email: chrahunt@gmail.com
License: UNKNOWN
Platform: UNKNOWN
Classifier: Programming Language :: Python :: 3
Requires-Dist: requests (~=2.22.0)
Requires-Dist: yarl (==1.3.0)
Provides-Extra: dev
Requires-Dist: aiohttp (~=3.5.4) ; extra == 'dev'
Requires-Dist: cryptography (~=2.7) ; extra == 'dev'
Requires-Dist: proxy.py (==0.3) ; extra == 'dev'
Requires-Dist: pytest (~=4.6.3) ; extra == 'dev'
Requires-Dist: pytest-aiohttp (~=0.3.0) ; extra == 'dev'
Requires-Dist: pytest-asyncio (~=0.10.0) ; extra == 'dev'
Requires-Dist: requests-async (==0.6.2) ; extra == 'dev'
